metagpt/__init__.py
metagpt/_compat.py
metagpt/config2.py
metagpt/const.py
metagpt/context.py
metagpt/context_mixin.py
metagpt/document.py
metagpt/llm.py
metagpt/logs.py
metagpt/repo_parser.py
metagpt/schema.py
metagpt/software_company.py
metagpt/startup.py
metagpt/subscription.py
metagpt/team.py
metagpt/actions/__init__.py
metagpt/actions/action.py
metagpt/actions/action_graph.py
metagpt/actions/action_node.py
metagpt/actions/action_outcls_registry.py
metagpt/actions/action_output.py
metagpt/actions/add_requirement.py
metagpt/actions/analyze_requirements.py
metagpt/actions/debug_error.py
metagpt/actions/design_api.py
metagpt/actions/design_api_an.py
metagpt/actions/design_api_review.py
metagpt/actions/execute_task.py
metagpt/actions/extract_readme.py
metagpt/actions/fix_bug.py
metagpt/actions/generate_questions.py
metagpt/actions/import_repo.py
metagpt/actions/invoice_ocr.py
metagpt/actions/prepare_documents.py
metagpt/actions/prepare_interview.py
metagpt/actions/project_management.py
metagpt/actions/project_management_an.py
metagpt/actions/rebuild_class_view.py
metagpt/actions/rebuild_sequence_view.py
metagpt/actions/research.py
metagpt/actions/run_code.py
metagpt/actions/search_and_summarize.py
metagpt/actions/search_enhanced_qa.py
metagpt/actions/skill_action.py
metagpt/actions/summarize_code.py
metagpt/actions/talk_action.py
metagpt/actions/write_code.py
metagpt/actions/write_code_an_draft.py
metagpt/actions/write_code_plan_and_change_an.py
metagpt/actions/write_code_review.py
metagpt/actions/write_docstring.py
metagpt/actions/write_prd.py
metagpt/actions/write_prd_an.py
metagpt/actions/write_prd_review.py
metagpt/actions/write_review.py
metagpt/actions/write_teaching_plan.py
metagpt/actions/write_test.py
metagpt/actions/write_tutorial.py
metagpt/actions/di/__init__.py
metagpt/actions/di/ask_review.py
metagpt/actions/di/execute_nb_code.py
metagpt/actions/di/run_command.py
metagpt/actions/di/write_analysis_code.py
metagpt/actions/di/write_plan.py
ve_metagpt-1.0.3.dist-info/licenses/LICENSE
ve_metagpt-1.0.3.dist-info/METADATA
ve_metagpt-1.0.3.dist-info/WHEEL
ve_metagpt-1.0.3.dist-info/entry_points.txt
ve_metagpt-1.0.3.dist-info/top_level.txt
ve_metagpt-1.0.3.dist-info/RECORD
